torch_swan/__init__.py
torch_swan/swan.py
torch_swan-0.0.11.dist-info/METADATA
torch_swan-0.0.11.dist-info/WHEEL
torch_swan-0.0.11.dist-info/entry_points.txt
torch_swan-0.0.11.dist-info/licenses/LICENSE
torch_swan-0.0.11.dist-info/RECORD
