Metadata-Version: 2.4
Name: torch_swan
Version: 0.0.11
Summary: SWAN is a library for training and deploying state-of-the-art deep learning models in PyTorch.
Project-URL: Homepage, https://github.com/ainilaha/swan
Project-URL: Issue, https://github.com/ainilaha/swan/issues
Project-URL: Repository, https://github.com/ainilaha/swan
Author-email: Laha Ale <ainilaha@gmail.com>
License: Copyright (C) 2025 Laha Ale
License-File: LICENSE
Classifier: Intended Audience :: Developers
Classifier: Intended Audience :: Science/Research
Classifier: License :: OSI Approved :: MIT License
Classifier: Operating System :: OS Independent
Classifier: Programming Language :: Python :: 3
Classifier: Topic :: Scientific/Engineering :: Artificial Intelligence
Requires-Python: >=3.8
Requires-Dist: numpy>=1.21
Requires-Dist: torch>=2.0
Requires-Dist: torchvision>=0.15
Provides-Extra: dev
Requires-Dist: build; extra == 'dev'
Requires-Dist: pytest; extra == 'dev'
Requires-Dist: ruff; extra == 'dev'
Requires-Dist: twine; extra == 'dev'
